shiftschema/__init__.py
shiftschema/exceptions.py
shiftschema/property.py
shiftschema/result.py
shiftschema/schema.py
shiftschema/translator.py
shiftschema/version.py
shiftschema/ext/__init__.py
shiftschema/ext/flask_wtf.py
shiftschema/filters/__init__.py
shiftschema/filters/abstract_filter.py
shiftschema/filters/add_http.py
shiftschema/filters/bleach.py
shiftschema/filters/digits.py
shiftschema/filters/linkify.py
shiftschema/filters/lowercase.py
shiftschema/filters/slugify.py
shiftschema/filters/stringify.py
shiftschema/filters/strip.py
shiftschema/filters/uppercase.py
shiftschema/translations/__init__.py
shiftschema/translations/en.py
shiftschema/translations/ru.py
shiftschema/validators/__init__.py
shiftschema/validators/abstract_validator.py
shiftschema/validators/choice.py
shiftschema/validators/digits.py
shiftschema/validators/email.py
shiftschema/validators/ip.py
shiftschema/validators/length.py
shiftschema/validators/multichoice.py
shiftschema/validators/not_empty.py
shiftschema/validators/required.py
shiftschema/validators/url.py
shiftschema-0.3.1.dist-info/LICENSE.txt
shiftschema-0.3.1.dist-info/METADATA
shiftschema-0.3.1.dist-info/WHEEL
shiftschema-0.3.1.dist-info/top_level.txt
shiftschema-0.3.1.dist-info/RECORD
