Metadata-Version: 2.1
Name: shiftschema
Version: 0.3.1
Summary: Filtering and validation library for arbitrary data structures
Home-page: https://github.com/projectshift/shift-schema
Download-URL: https://github.com/projectshift/shift-schema/archive/0.3.1.tar.gz
Author: Dmitry Belyakov
Author-email: dmitrybelyakov@gmail.com
License: MIT License
Keywords: python3,validation,filtering,schema,webapp,api
Classifier: Development Status :: 4 - Beta
Classifier: License :: OSI Approved :: MIT License
Classifier: Intended Audience :: Developers
Classifier: Intended Audience :: Information Technology
Classifier: Programming Language :: Python :: 3
Classifier: Environment :: Web Environment
Classifier: Framework :: Flask
Classifier: Topic :: Utilities
License-File: LICENSE.txt
Requires-Dist: bleach <4.0.0,>=3.3.0
Requires-Dist: python-slugify <6.0.0,>=5.0.2
